llmjudge/__init__.py
llmjudge/core.py
llmjudge-0.1.0.dist-info/METADATA
llmjudge-0.1.0.dist-info/WHEEL
llmjudge-0.1.0.dist-info/top_level.txt
llmjudge-0.1.0.dist-info/RECORD
