Metadata-Version: 2.1
Name: llmjudge
Version: 0.1.0
Summary: A package for evaluating language model outputs.
Author-email: weichiang <weichiang@berkeley.edu>
Project-URL: Homepage, https://github.com/your_username/llmjudge
Project-URL: Issue Tracker, https://github.com/your_username/llmjudge/issues
Keywords: LLM,evaluation,NLP
Classifier: Programming Language :: Python :: 3
Classifier: License :: OSI Approved :: MIT License
Classifier: Operating System :: OS Independent
Classifier: Intended Audience :: Developers
Classifier: Topic :: Software Development :: Libraries :: Python Modules
Requires-Python: >=3.7
